{
  "22000012": {
    "id": "22000012",
    "name": "Neumarkt",
    "lat": 50.9368,
    "lng": 6.9477
  },
  "22000019": {
    "id": "22000019",
    "name": "Dom/Hbf",
    "lat": 50.9429,
    "lng": 6.9582
  },
  "22000238": {
    "id": "22000238",
    "name": "Gutenbergstraße",
    "lat": 50.9289,
    "lng": 6.9458
  },
  "22000018": {
    "id": "22000018",
    "name": "Friesenplatz",
    "lat": 50.9388,
    "lng": 6.9428
  },
  "22000023": {
    "id": "22000023",
    "name": "Heumarkt",
    "lat": 50.9356,
    "lng": 6.9615
  },
  "22000030": {
    "id": "22000030",
    "name": "Appellhofplatz",
    "lat": 50.9398,
    "lng": 6.9523
  },
  "22000025": {
    "id": "22000025",
    "name": "Rathaus",
    "lat": 50.9378,
    "lng": 6.9575
  },
  "22000100": {
    "id": "22000100",
    "name": "Barbarossaplatz",
    "lat": 50.9278,
    "lng": 6.9418
  },
  "22000120": {
    "id": "22000120",
    "name": "Rudolfplatz",
    "lat": 50.9358,
    "lng": 6.9428
  },
  "22000015": {
    "id": "22000015",
    "name": "Ebertplatz",
    "lat": 50.9488,
    "lng": 6.9618
  },
  "22000045": {
    "id": "22000045",
    "name": "Hansaring",
    "lat": 50.9468,
    "lng": 6.9488
  },
  "22000050": {
    "id": "22000050",
    "name": "Christophstraße/Mediapark",
    "lat": 50.9458,
    "lng": 6.9438
  },
  "22000060": {
    "id": "22000060",
    "name": "Körnerstraße",
    "lat": 50.9328,
    "lng": 6.9378
  },
  "22000070": {
    "id": "22000070",
    "name": "Zülpicher Platz",
    "lat": 50.9298,
    "lng": 6.9328
  },
  "22000080": {
    "id": "22000080",
    "name": "Chlodwigplatz",
    "lat": 50.9248,
    "lng": 6.9558
  },
  "22000090": {
    "id": "22000090",
    "name": "Severinstraße",
    "lat": 50.9298,
    "lng": 6.9598
  },
  "22000110": {
    "id": "22000110",
    "name": "Ubierring",
    "lat": 50.9238,
    "lng": 6.9608
  },
  "22000130": {
    "id": "22000130",
    "name": "Poststraße",
    "lat": 50.9338,
    "lng": 6.9528
  },
  "22000140": {
    "id": "22000140",
    "name": "Mauritiuskirche",
    "lat": 50.9448,
    "lng": 6.9668
  },
  "22000150": {
    "id": "22000150",
    "name": "Reichenspergerplatz",
    "lat": 50.9498,
    "lng": 6.9708
  },
  "22000160": {
    "id": "22000160",
    "name": "Kalk Post",
    "lat": 50.9408,
    "lng": 7.0008
  },
  "22000170": {
    "id": "22000170",
    "name": "Kalk Kapelle",
    "lat": 50.9358,
    "lng": 7.0108
  },
  "22000180": {
    "id": "22000180",
    "name": "Wiener Platz",
    "lat": 50.9388,
    "lng": 6.9808
  },
  "22000190": {
    "id": "22000190",
    "name": "Deutzer Freiheit",
    "lat": 50.9358,
    "lng": 6.9758
  },
  "22000200": {
    "id": "22000200",
    "name": "Deutz/Messe",
    "lat": 50.9408,
    "lng": 6.9808
  }
}
